hello/__init__.py
hello/main.py
simple_temp_test-0.0.5.dist-info/METADATA
simple_temp_test-0.0.5.dist-info/WHEEL
simple_temp_test-0.0.5.dist-info/entry_points.txt
simple_temp_test-0.0.5.dist-info/top_level.txt
simple_temp_test-0.0.5.dist-info/RECORD
