Metadata-Version: 2.1
Name: simple-temp-test
Version: 0.0.5
Summary: UNKNOWN
Home-page: UNKNOWN
Author: Andrea
License: UNKNOWN
Platform: UNKNOWN
Classifier: Programming Language :: Python :: 3
Classifier: License :: OSI Approved :: MIT License
Classifier: Operating System :: OS Independent
Requires-Python: >=3.8
Requires-Dist: pytest
